{
  "legislative_session": "2026",
  "identifier": "HB 2934",
  "title": "Modifies provisions governing the Regional Convention and Visitors Commission and the Regional Convention and Sports Complex Authority in St. Louis City and St. Louis County",
  "from_organization": "~{\"classification\": \"lower\"}",
  "classification": [
    "bill"
  ],
  "subject": [
    "BOARDS, COMMISSIONS, COMMITTEES, AND COUNCILS",
    "ENTERTAINMENT, SPORTS AND AMUSEMENTS",
    "GOVERNOR AND LT. GOVERNOR",
    "SAINT LOUIS CITY",
    "SAINT LOUIS COUNTY",
    "TOURISM"
  ],
  "abstracts": [],
  "other_titles": [
    {
      "note": "official",
      "title": "HB 2934"
    }
  ],
  "other_identifiers": [],
  "actions": [
    {
      "description": "Introduced and Read First Time (H)",
      "date": "2026-01-13T06:00:00+00:00",
      "organization_id": "~{\"classification\": \"lower\"}",
      "classification": [
        "introduction"
      ],
      "related_entities": [],
      "_processing": {
        "log_file_created": "2026-01-14T12:41:27Z"
      }
    },
    {
      "description": "Read Second Time (H)",
      "date": "2026-01-14T06:00:00+00:00",
      "organization_id": "~{\"classification\": \"lower\"}",
      "classification": [
        "reading-2"
      ],
      "related_entities": [],
      "_processing": {
        "log_file_created": "2026-01-15T12:40:53Z"
      }
    },
    {
      "description": "Referred: Special Committee on Intergovernmental Affairs(H)",
      "date": "2026-01-22T06:00:00+00:00",
      "organization_id": "~{\"classification\": \"lower\"}",
      "classification": [
        "referral-committee"
      ],
      "related_entities": [],
      "_processing": {
        "log_file_created": "2026-01-23T12:42:11Z"
      }
    },
    {
      "description": "Public Hearing Completed (H)",
      "date": "2026-01-29T06:00:00+00:00",
      "organization_id": "~{\"classification\": \"lower\"}",
      "classification": [],
      "related_entities": [],
      "_processing": {
        "log_file_created": "2026-01-30T12:51:06Z"
      }
    },
    {
      "description": "Executive Session Completed (H)",
      "date": "2026-02-02T06:00:00+00:00",
      "organization_id": "~{\"classification\": \"lower\"}",
      "classification": [],
      "related_entities": [],
      "_processing": {
        "log_file_created": "2026-02-03T12:55:07Z"
      }
    },
    {
      "description": "Voted Do Pass (H)",
      "date": "2026-02-02T06:00:00+00:00",
      "organization_id": "~{\"classification\": \"lower\"}",
      "classification": [
        "committee-passage"
      ],
      "related_entities": [],
      "_processing": {
        "log_file_created": "2026-02-03T12:55:07Z"
      }
    },
    {
      "description": "Reported Do Pass (H) - AYES: 12 NOES: 1 PRESENT: 0",
      "date": "2026-02-03T06:00:00+00:00",
      "organization_id": "~{\"classification\": \"lower\"}",
      "classification": [
        "committee-passage"
      ],
      "related_entities": [],
      "_processing": {
        "log_file_created": "2026-02-04T12:54:35Z"
      }
    },
    {
      "description": "Referred: Rules - Legislative(H)",
      "date": "2026-02-03T06:00:00+00:00",
      "organization_id": "~{\"classification\": \"lower\"}",
      "classification": [
        "referral-committee"
      ],
      "related_entities": [],
      "_processing": {
        "log_file_created": "2026-02-04T12:54:35Z"
      }
    },
    {
      "description": "Executive Session Completed (H)",
      "date": "2026-02-09T06:00:00+00:00",
      "organization_id": "~{\"classification\": \"lower\"}",
      "classification": [],
      "related_entities": [],
      "_processing": {
        "log_file_created": "2026-02-10T13:07:47Z"
      }
    },
    {
      "description": "Voted Do Pass (H)",
      "date": "2026-02-09T06:00:00+00:00",
      "organization_id": "~{\"classification\": \"lower\"}",
      "classification": [
        "committee-passage"
      ],
      "related_entities": [],
      "_processing": {
        "log_file_created": "2026-02-10T13:07:47Z"
      }
    },
    {
      "description": "Reported Do Pass (H) - AYES: 10 NOES: 0 PRESENT: 2",
      "date": "2026-02-09T06:00:00+00:00",
      "organization_id": "~{\"classification\": \"lower\"}",
      "classification": [
        "committee-passage"
      ],
      "related_entities": [],
      "_processing": {
        "log_file_created": "2026-02-10T13:07:47Z"
      }
    }
  ],
  "sponsorships": [
    {
      "name": "Brad Christ",
      "classification": "primary",
      "entity_type": "person",
      "primary": true,
      "person_id": "~{\"name\": \"Brad Christ\"}",
      "organization_id": null
    },
    {
      "name": "Marty Joe Murray",
      "classification": "cosponsor",
      "entity_type": "person",
      "primary": false,
      "person_id": "~{\"name\": \"Marty Joe Murray\"}",
      "organization_id": null
    }
  ],
  "related_bills": [],
  "versions": [
    {
      "note": "Introduced",
      "links": [
        {
          "url": "https://documents.house.mo.gov/billtracking/bills261/hlrbillspdf/6164H.01I.pdf",
          "media_type": "application/pdf"
        }
      ],
      "date": "",
      "classification": ""
    }
  ],
  "documents": [
    {
      "note": "Bill Summary (Introduced)",
      "links": [
        {
          "url": "https://documents.house.mo.gov/billtracking/bills261/sumpdf/HB2934I.pdf",
          "media_type": "application/pdf"
        }
      ],
      "date": "",
      "classification": ""
    },
    {
      "note": "Bill Summary (Committee)",
      "links": [
        {
          "url": "https://documents.house.mo.gov/billtracking/bills261/sumpdf/HB2934C.pdf",
          "media_type": "application/pdf"
        }
      ],
      "date": "",
      "classification": ""
    },
    {
      "note": "Fiscal Note 6164H.01I.ORG",
      "links": [
        {
          "url": "https://documents.house.mo.gov/billtracking/bills261/fiscal/fispdf/6164H.01I.ORG.pdf",
          "media_type": "application/pdf"
        }
      ],
      "date": "",
      "classification": ""
    },
    {
      "note": "Bill Summary (Witnesses)",
      "links": [
        {
          "url": "https://documents.house.mo.gov/billtracking/bills261/witnesses/HB2934Testimony1-29.pdf",
          "media_type": "application/pdf"
        }
      ],
      "date": "",
      "classification": ""
    }
  ],
  "citations": [],
  "sources": [
    {
      "url": "https://www.house.mo.gov/BillContent.aspx?bill=HB2934&year=2026&code=R&style=new",
      "note": ""
    },
    {
      "url": "https://house.mo.gov/billactions.aspx?bill=HB2934&year=2026&code=R",
      "note": ""
    }
  ],
  "extras": {},
  "jurisdiction": {
    "id": "ocd-jurisdiction/country:us/state:mo/government",
    "name": "Missouri",
    "classification": "state",
    "division_id": "ocd-division/country:us/state:mo"
  },
  "_processing": {
    "logs_latest_update": "2026-02-10T13:07:47Z"
  }
}